kermi_xcenter/__init__.py
kermi_xcenter/client.py
kermi_xcenter/exceptions.py
kermi_xcenter/py.typed
kermi_xcenter/registers.py
kermi_xcenter/types.py
kermi_xcenter/http/__init__.py
kermi_xcenter/http/client.py
kermi_xcenter/http/mapping.py
kermi_xcenter/http/models.py
kermi_xcenter/http/session.py
kermi_xcenter/models/__init__.py
kermi_xcenter/models/base.py
kermi_xcenter/models/heat_pump.py
kermi_xcenter/models/storage_system.py
kermi_xcenter/models/universal_module.py
kermi_xcenter/utils/__init__.py
kermi_xcenter/utils/conversions.py
kermi_xcenter/utils/discovery.py
kermi_xcenter-0.3.1.dist-info/licenses/LICENSE
kermi_xcenter-0.3.1.dist-info/METADATA
kermi_xcenter-0.3.1.dist-info/WHEEL
kermi_xcenter-0.3.1.dist-info/top_level.txt
kermi_xcenter-0.3.1.dist-info/RECORD
