Metadata-Version: 2.4
Name: kermi-xcenter
Version: 0.3.1
Summary: Async Python interface for Kermi heat pumps via Modbus and HTTP
Author-email: Jeremias Reith <jr42@users.noreply.github.com>
License: Apache-2.0
Project-URL: Homepage, https://github.com/jr42/py-kermi-xcenter
Project-URL: Documentation, https://github.com/jr42/py-kermi-xcenter#readme
Project-URL: Repository, https://github.com/jr42/py-kermi-xcenter
Project-URL: Issues, https://github.com/jr42/py-kermi-xcenter/issues
Keywords: kermi,modbus,heat-pump,async,iot
Classifier: Development Status :: 3 - Alpha
Classifier: Intended Audience :: Developers
Classifier: License :: OSI Approved :: Apache Software License
Classifier: Programming Language :: Python :: 3
Classifier: Programming Language :: Python :: 3.12
Classifier: Programming Language :: Python :: 3.13
Classifier: Framework :: AsyncIO
Requires-Python: >=3.12
License-File: LICENSE
Requires-Dist: pymodbus>=3.6.0
Requires-Dist: aiohttp>=3.9.0
Provides-Extra: dev
Requires-Dist: pytest>=7.4; extra == "dev"
Requires-Dist: pytest-cov>=4.1; extra == "dev"
Requires-Dist: pytest-asyncio>=0.21; extra == "dev"
Requires-Dist: ruff>=0.1.0; extra == "dev"
Requires-Dist: black>=23.0; extra == "dev"
Requires-Dist: mypy>=1.7; extra == "dev"
Requires-Dist: pre-commit>=3.5; extra == "dev"
Provides-Extra: rtu
Requires-Dist: pyserial>=3.5; extra == "rtu"
Dynamic: license-file
